opaipy/Library/opaipyAI.py
opaipy/Library/opaipyBase.py
opaipy/Library/opaipyConfig.py
opaipy/Library/opaipyConfiger.py
opaipy/Library/opaipyDeclare.py
opaipy/Library/opaipyException.py
opaipy/Library/opaipyGlobals.py
opaipy-1.0.2.dist-info/METADATA
opaipy-1.0.2.dist-info/WHEEL
opaipy-1.0.2.dist-info/top_level.txt
opaipy-1.0.2.dist-info/RECORD
